nucleobench/__init__.py
nucleobench/common/__init__.py
nucleobench/common/argparse_lib.py
nucleobench/common/attribution_lib_torch.py
nucleobench/common/attribution_lib_torch_test.py
nucleobench/common/constants.py
nucleobench/common/gcp_utils.py
nucleobench/common/memory_utils.py
nucleobench/common/priority_queue.py
nucleobench/common/priority_queue_test.py
nucleobench/common/string_utils.py
nucleobench/common/string_utils_test.py
nucleobench/common/testing_utils.py
nucleobench/common/testing_utils_test.py
nucleobench/optimizations/__init__.py
nucleobench/optimizations/model_class.py
nucleobench/optimizations/optimization_class.py
nucleobench/optimizations/typing.py
nucleobench/optimizations/utils.py
nucleobench/optimizations/utils_test.py
nucleobench/optimizations/ada/__init__.py
nucleobench/optimizations/ada/ada_utils.py
nucleobench/optimizations/ada/ada_utils_test.py
nucleobench/optimizations/ada/adabeam/__init__.py
nucleobench/optimizations/ada/adabeam/adabeam.py
nucleobench/optimizations/ada/adabeam/adabeam_test.py
nucleobench/optimizations/ada/adalead/__init__.py
nucleobench/optimizations/ada/adalead/adalead_ref.py
nucleobench/optimizations/ada/adalead/adalead_ref_test.py
nucleobench/optimizations/beam_search/__init__.py
nucleobench/optimizations/beam_search/beam_ordered.py
nucleobench/optimizations/beam_search/beam_ordered_test.py
nucleobench/optimizations/beam_search/beam_unordered.py
nucleobench/optimizations/beam_search/beam_unordered_test.py
nucleobench/optimizations/beam_search/beam_utils.py
nucleobench/optimizations/beam_search/beam_utils_test.py
nucleobench/optimizations/directed_evolution/__init__.py
nucleobench/optimizations/directed_evolution/directed_evolution.py
nucleobench/optimizations/directed_evolution/directed_evolution_module.py
nucleobench/optimizations/directed_evolution/directed_evolution_module_test.py
nucleobench/optimizations/dummy/__init__.py
nucleobench/optimizations/dummy/random_perturbation.py
nucleopt-1.0.4.dist-info/licenses/LICENSE
nucleopt-1.0.4.dist-info/METADATA
nucleopt-1.0.4.dist-info/WHEEL
nucleopt-1.0.4.dist-info/top_level.txt
nucleopt-1.0.4.dist-info/RECORD
