Metadata-Version: 2.4
Name: nucleopt
Version: 1.0.4
Summary: Optimizers from the nucleobench package.
Author-email: Move37 Labs <joel.shor@move37labs.com>
Project-URL: Homepage, https://github.com/move37-labs/nucleobench
Project-URL: Bug Tracker, https://github.com/move37-labs/nucleobench/issues
Classifier: Programming Language :: Python :: 3
Classifier: Programming Language :: Python :: 3.10
Classifier: Programming Language :: Python :: 3.11
Classifier: Programming Language :: Python :: 3.12
Classifier: Operating System :: OS Independent
Requires-Python: >=3.10
License-File: LICENSE
Requires-Dist: torch>=2.2
Requires-Dist: numpy>=1.16
Requires-Dist: scipy
Requires-Dist: pandas
Requires-Dist: h5py
Requires-Dist: pyarrow
Requires-Dist: google-cloud-storage
Provides-Extra: dev
Requires-Dist: pytest; extra == "dev"
Requires-Dist: coverage; extra == "dev"
Requires-Dist: pyclean; extra == "dev"
Dynamic: license-file
